structa/__init__.py
structa/analyzer.py
structa/chars.py
structa/collections.py
structa/conversions.py
structa/errors.py
structa/format.py
structa/source.py
structa/types.py
structa/xml.py
structa/ui/__init__.py
structa/ui/cli.py
structa/ui/cli.xsl
structa-0.4.dist-info/LICENSE.txt
structa-0.4.dist-info/METADATA
structa-0.4.dist-info/WHEEL
structa-0.4.dist-info/entry_points.txt
structa-0.4.dist-info/top_level.txt
structa-0.4.dist-info/RECORD
