Metadata-Version: 2.1
Name: structa
Version: 0.4
Summary: Analyzes data files for common structures
Author: Dave Jones
Author-email: dave@waveform.org.uk
License: UNKNOWN
Project-URL: Documentation, https://structa.readthedocs.io/
Project-URL: Source Code, https://github.com/waveform80/structa
Project-URL: Issue Tracker, https://github.com/waveform80/structa/issues
Keywords: json yaml csv data analysis
Platform: UNKNOWN
Classifier: Development Status :: 3 - Alpha
Classifier: Environment :: Console
Classifier: Intended Audience :: Developers
Classifier: License :: OSI Approved :: GNU General Public License v2 or later (GPLv2+)
Classifier: Operating System :: OS Independent
Classifier: Programming Language :: Python
Classifier: Programming Language :: Python :: 3
Classifier: Programming Language :: Python :: 3.5
Classifier: Programming Language :: Python :: 3.6
Classifier: Programming Language :: Python :: 3.7
Classifier: Programming Language :: Python :: 3.8
Classifier: Programming Language :: Python :: 3.9
Classifier: Programming Language :: Python :: 3.10
Classifier: Programming Language :: Python :: Implementation :: PyPy
Requires-Python: >=3.5
License-File: LICENSE.txt
Requires-Dist: setuptools
Requires-Dist: lxml
Requires-Dist: chardet
Requires-Dist: blessings
Requires-Dist: tqdm
Requires-Dist: python-dateutil
Provides-Extra: doc
Requires-Dist: sphinx ; extra == 'doc'
Requires-Dist: sphinx-rtd-theme ; extra == 'doc'
Provides-Extra: test
Requires-Dist: pytest ; extra == 'test'
Requires-Dist: pytest-cov ; extra == 'test'
Provides-Extra: yaml
Requires-Dist: ruamel.yaml ; extra == 'yaml'
